src/__init__.py
src/main.py
src/config/settings.py
src/services/download/youtube.py
src/services/transcription/assemblyai.py
src/services/transcription/base.py
src/services/transcription/deepgram.py
src/services/transcription/gladia.py
src/services/transcription/speechmatics.py
iflow_mcp_mcp_video_digest-0.1.0.dist-info/METADATA
iflow_mcp_mcp_video_digest-0.1.0.dist-info/WHEEL
iflow_mcp_mcp_video_digest-0.1.0.dist-info/entry_points.txt
iflow_mcp_mcp_video_digest-0.1.0.dist-info/licenses/LICENSE
iflow_mcp_mcp_video_digest-0.1.0.dist-info/RECORD
