Metadata-Version: 2.4
Name: iflow-mcp_mcp-video-digest
Version: 0.1.0
Summary: MCP Server for transcribing videos via video links and summarizing video content
Author: R-lz
License-File: LICENSE
Requires-Python: >=3.11
Requires-Dist: mcp>=1.6.0
Requires-Dist: python-dotenv>=1.1.0
Requires-Dist: requests>=2.32.3
Requires-Dist: speechmatics-python>=3.0.3
Requires-Dist: yt-dlp>=2025.3.31
